reachy_pyluos_hal/__init__.py
reachy_pyluos_hal/config.py
reachy_pyluos_hal/device.py
reachy_pyluos_hal/discovery.py
reachy_pyluos_hal/dynamixel.py
reachy_pyluos_hal/fan.py
reachy_pyluos_hal/force_sensor.py
reachy_pyluos_hal/joint.py
reachy_pyluos_hal/joint_hal.py
reachy_pyluos_hal/orbita.py
reachy_pyluos_hal/orbita_kinematic_model.py
reachy_pyluos_hal/pycore.py
reachy_pyluos_hal/reachy.py
reachy_pyluos_hal/register.py
reachy_pyluos_hal/config/head.yaml
reachy_pyluos_hal/config/left_arm.yaml
reachy_pyluos_hal/config/left_arm_advanced.yaml
reachy_pyluos_hal/config/orbita.yaml
reachy_pyluos_hal/config/right_arm.yaml
reachy_pyluos_hal/config/right_arm_advanced.yaml
reachy_pyluos_hal/tools/__init__.py
reachy_pyluos_hal/tools/dynamixel_config.py
reachy_pyluos_hal/tools/reachy_dynamixel_config.py
reachy_pyluos_hal/tools/reachy_identify_model.py
reachy_pyluos_hal-0.3.1.dist-info/LICENSE
reachy_pyluos_hal-0.3.1.dist-info/METADATA
reachy_pyluos_hal-0.3.1.dist-info/WHEEL
reachy_pyluos_hal-0.3.1.dist-info/entry_points.txt
reachy_pyluos_hal-0.3.1.dist-info/top_level.txt
reachy_pyluos_hal-0.3.1.dist-info/RECORD
