Metadata-Version: 2.1
Name: reachy-pyluos-hal
Version: 0.3.1
Summary: Reachy hardware library controller
Home-page: https://github.com/pollen-robotics/reachy_pyluos_hal
Author: Pollen Robotics
Author-email: contact@pollen-robotics.com
License: UNKNOWN
Platform: UNKNOWN
License-File: LICENSE
Requires-Dist: numpy
Requires-Dist: pyquaternion
Requires-Dist: pyserial
Requires-Dist: PyYAML
Requires-Dist: scipy
Requires-Dist: sklearn
